README.md
setup.py
pyLdtk.egg-info/PKG-INFO
pyLdtk.egg-info/SOURCES.txt
pyLdtk.egg-info/dependency_links.txt
pyLdtk.egg-info/requires.txt
pyLdtk.egg-info/top_level.txt
src/__init__.py
src/pyLdtk.py